[
  {
    "ContainingType": "BookStore.Controllers.AccountController",
    "Method": "GetAllAsync",
    "RelativePath": "api/Account",
    "HttpMethod": "GET",
    "IsController": true,
    "Order": 0,
    "Parameters": [
      {
        "Name": "page",
        "Type": "System.Int32",
        "IsRequired": false
      },
      {
        "Name": "pageSize",
        "Type": "System.Int32",
        "IsRequired": false
      },
      {
        "Name": "searchUsername",
        "Type": "System.String",
        "IsRequired": false
      }
    ],
    "ReturnTypes": []
  },
  {
    "ContainingType": "BookStore.Controllers.AccountController",
    "Method": "GetById",
    "RelativePath": "api/Account/{id}",
    "HttpMethod": "GET",
    "IsController": true,
    "Order": 0,
    "Parameters": [
      {
        "Name": "id",
        "Type": "System.Int32",
        "IsRequired": true
      }
    ],
    "ReturnTypes": []
  },
  {
    "ContainingType": "BookStore.Controllers.AccountController",
    "Method": "Update",
    "RelativePath": "api/Account/{id}",
    "HttpMethod": "PUT",
    "IsController": true,
    "Order": 0,
    "Parameters": [
      {
        "Name": "id",
        "Type": "System.Int32",
        "IsRequired": true
      },
      {
        "Name": "accountDto",
        "Type": "BookStore.Dtos.AccountDto",
        "IsRequired": true
      }
    ],
    "ReturnTypes": []
  },
  {
    "ContainingType": "BookStore.Controllers.AccountController",
    "Method": "Delete",
    "RelativePath": "api/Account/{id}",
    "HttpMethod": "DELETE",
    "IsController": true,
    "Order": 0,
    "Parameters": [
      {
        "Name": "id",
        "Type": "System.Int32",
        "IsRequired": true
      }
    ],
    "ReturnTypes": []
  },
  {
    "ContainingType": "BookStore.Controllers.AccountController",
    "Method": "ChangeActive",
    "RelativePath": "api/Account/{id}/changeActive",
    "HttpMethod": "PUT",
    "IsController": true,
    "Order": 0,
    "Parameters": [
      {
        "Name": "id",
        "Type": "System.Int32",
        "IsRequired": true
      }
    ],
    "ReturnTypes": []
  },
  {
    "ContainingType": "BookStore.Controllers.AccountController",
    "Method": "ChangePassword",
    "RelativePath": "api/Account/{id}/changePassword",
    "HttpMethod": "PUT",
    "IsController": true,
    "Order": 0,
    "Parameters": [
      {
        "Name": "id",
        "Type": "System.Int32",
        "IsRequired": true
      },
      {
        "Name": "changePasswordDto",
        "Type": "BookStore.Dtos.ChangePasswordDto",
        "IsRequired": true
      }
    ],
    "ReturnTypes": []
  },
  {
    "ContainingType": "BookStore.Controllers.AccountController",
    "Method": "ResetPassword",
    "RelativePath": "api/Account/{id}/resetPassword",
    "HttpMethod": "PUT",
    "IsController": true,
    "Order": 0,
    "Parameters": [
      {
        "Name": "id",
        "Type": "System.Int32",
        "IsRequired": true
      }
    ],
    "ReturnTypes": []
  },
  {
    "ContainingType": "BookStore.Controllers.AccountController",
    "Method": "CreateAccountAndUser",
    "RelativePath": "api/Account/create",
    "HttpMethod": "POST",
    "IsController": true,
    "Order": 0,
    "Parameters": [
      {
        "Name": "request",
        "Type": "BookStore.Dtos.AccountAndUserDto",
        "IsRequired": true
      }
    ],
    "ReturnTypes": []
  },
  {
    "ContainingType": "BookStore.Controllers.AccountController",
    "Method": "Login",
    "RelativePath": "api/Account/login",
    "HttpMethod": "POST",
    "IsController": true,
    "Order": 0,
    "Parameters": [
      {
        "Name": "loginDto",
        "Type": "BookStore.Dtos.LoginDto",
        "IsRequired": true
      }
    ],
    "ReturnTypes": []
  },
  {
    "ContainingType": "BookStore.Controllers.AccountController",
    "Method": "RefreshToken",
    "RelativePath": "api/Account/refresh",
    "HttpMethod": "POST",
    "IsController": true,
    "Order": 0,
    "Parameters": [
      {
        "Name": "refreshToken",
        "Type": "System.String",
        "IsRequired": true
      }
    ],
    "ReturnTypes": []
  },
  {
    "ContainingType": "BookStore.Controllers.BookController",
    "Method": "GetAllBooks",
    "RelativePath": "api/Book",
    "HttpMethod": "GET",
    "IsController": true,
    "Order": 0,
    "Parameters": [
      {
        "Name": "page",
        "Type": "System.Int32",
        "IsRequired": false
      },
      {
        "Name": "pageSize",
        "Type": "System.Int32",
        "IsRequired": false
      },
      {
        "Name": "category",
        "Type": "System.String",
        "IsRequired": false
      },
      {
        "Name": "sortBy",
        "Type": "System.String",
        "IsRequired": false
      },
      {
        "Name": "isDescending",
        "Type": "System.Boolean",
        "IsRequired": false
      },
      {
        "Name": "searchTerm",
        "Type": "System.String",
        "IsRequired": false
      }
    ],
    "ReturnTypes": []
  },
  {
    "ContainingType": "BookStore.Controllers.BookController",
    "Method": "CreateBook",
    "RelativePath": "api/Book",
    "HttpMethod": "POST",
    "IsController": true,
    "Order": 0,
    "Parameters": [
      {
        "Name": "bookDto",
        "Type": "BookStore.Dtos.BookDto",
        "IsRequired": true
      }
    ],
    "ReturnTypes": []
  },
  {
    "ContainingType": "BookStore.Controllers.BookController",
    "Method": "AddCategoryJoinBook",
    "RelativePath": "api/Book/{bookId}/categories/{categoryId}",
    "HttpMethod": "POST",
    "IsController": true,
    "Order": 0,
    "Parameters": [
      {
        "Name": "bookId",
        "Type": "System.Int32",
        "IsRequired": true
      },
      {
        "Name": "categoryId",
        "Type": "System.Int32",
        "IsRequired": true
      }
    ],
    "ReturnTypes": []
  },
  {
    "ContainingType": "BookStore.Controllers.BookController",
    "Method": "GetBookById",
    "RelativePath": "api/Book/{id}",
    "HttpMethod": "GET",
    "IsController": true,
    "Order": 0,
    "Parameters": [
      {
        "Name": "id",
        "Type": "System.Int32",
        "IsRequired": true
      }
    ],
    "ReturnTypes": []
  },
  {
    "ContainingType": "BookStore.Controllers.BookController",
    "Method": "UpdateBook",
    "RelativePath": "api/Book/{id}",
    "HttpMethod": "PUT",
    "IsController": true,
    "Order": 0,
    "Parameters": [
      {
        "Name": "id",
        "Type": "System.Int32",
        "IsRequired": true
      },
      {
        "Name": "bookDto",
        "Type": "BookStore.Dtos.BookDto",
        "IsRequired": true
      }
    ],
    "ReturnTypes": []
  },
  {
    "ContainingType": "BookStore.Controllers.BookController",
    "Method": "DeleteBook",
    "RelativePath": "api/Book/{id}",
    "HttpMethod": "DELETE",
    "IsController": true,
    "Order": 0,
    "Parameters": [
      {
        "Name": "id",
        "Type": "System.Int32",
        "IsRequired": true
      }
    ],
    "ReturnTypes": []
  },
  {
    "ContainingType": "BookStore.Controllers.BookController",
    "Method": "GetCategoryByBookId",
    "RelativePath": "api/Book/{id}/categories",
    "HttpMethod": "GET",
    "IsController": true,
    "Order": 0,
    "Parameters": [
      {
        "Name": "id",
        "Type": "System.Int32",
        "IsRequired": true
      }
    ],
    "ReturnTypes": []
  },
  {
    "ContainingType": "BookStore.Controllers.CartController",
    "Method": "GetAllCarts",
    "RelativePath": "api/Cart",
    "HttpMethod": "GET",
    "IsController": true,
    "Order": 0,
    "Parameters": [],
    "ReturnTypes": []
  },
  {
    "ContainingType": "BookStore.Controllers.CartController",
    "Method": "CreateCart",
    "RelativePath": "api/Cart",
    "HttpMethod": "POST",
    "IsController": true,
    "Order": 0,
    "Parameters": [
      {
        "Name": "cartDto",
        "Type": "BookStore.Dtos.CartDto",
        "IsRequired": true
      }
    ],
    "ReturnTypes": []
  },
  {
    "ContainingType": "BookStore.Controllers.CartController",
    "Method": "GetCartById",
    "RelativePath": "api/Cart/{id}",
    "HttpMethod": "GET",
    "IsController": true,
    "Order": 0,
    "Parameters": [
      {
        "Name": "id",
        "Type": "System.Int32",
        "IsRequired": true
      }
    ],
    "ReturnTypes": []
  },
  {
    "ContainingType": "BookStore.Controllers.CartController",
    "Method": "UpdateCart",
    "RelativePath": "api/Cart/{id}",
    "HttpMethod": "PUT",
    "IsController": true,
    "Order": 0,
    "Parameters": [
      {
        "Name": "id",
        "Type": "System.Int32",
        "IsRequired": true
      },
      {
        "Name": "cartDto",
        "Type": "BookStore.Dtos.CartDto",
        "IsRequired": true
      }
    ],
    "ReturnTypes": []
  },
  {
    "ContainingType": "BookStore.Controllers.CartController",
    "Method": "DeleteCart",
    "RelativePath": "api/Cart/{id}",
    "HttpMethod": "DELETE",
    "IsController": true,
    "Order": 0,
    "Parameters": [
      {
        "Name": "id",
        "Type": "System.Int32",
        "IsRequired": true
      }
    ],
    "ReturnTypes": []
  },
  {
    "ContainingType": "BookStore.Controllers.CartController",
    "Method": "GetCartByUserId",
    "RelativePath": "api/Cart/user/{userId}",
    "HttpMethod": "GET",
    "IsController": true,
    "Order": 0,
    "Parameters": [
      {
        "Name": "userId",
        "Type": "System.Int32",
        "IsRequired": true
      }
    ],
    "ReturnTypes": []
  },
  {
    "ContainingType": "BookStore.Controllers.CartItemController",
    "Method": "GetAllCartItems",
    "RelativePath": "api/CartItem",
    "HttpMethod": "GET",
    "IsController": true,
    "Order": 0,
    "Parameters": [],
    "ReturnTypes": []
  },
  {
    "ContainingType": "BookStore.Controllers.CartItemController",
    "Method": "CreateCartItem",
    "RelativePath": "api/CartItem",
    "HttpMethod": "POST",
    "IsController": true,
    "Order": 0,
    "Parameters": [
      {
        "Name": "cartItemDto",
        "Type": "BookStore.Dtos.CartItemDto",
        "IsRequired": true
      }
    ],
    "ReturnTypes": []
  },
  {
    "ContainingType": "BookStore.Controllers.CartItemController",
    "Method": "GetCartItemById",
    "RelativePath": "api/CartItem/{id}",
    "HttpMethod": "GET",
    "IsController": true,
    "Order": 0,
    "Parameters": [
      {
        "Name": "id",
        "Type": "System.Int32",
        "IsRequired": true
      }
    ],
    "ReturnTypes": []
  },
  {
    "ContainingType": "BookStore.Controllers.CartItemController",
    "Method": "UpdateCartItem",
    "RelativePath": "api/CartItem/{id}",
    "HttpMethod": "PUT",
    "IsController": true,
    "Order": 0,
    "Parameters": [
      {
        "Name": "id",
        "Type": "System.Int32",
        "IsRequired": true
      },
      {
        "Name": "cartItemDto",
        "Type": "BookStore.Dtos.CartItemDto",
        "IsRequired": true
      }
    ],
    "ReturnTypes": []
  },
  {
    "ContainingType": "BookStore.Controllers.CartItemController",
    "Method": "DeleteCartItem",
    "RelativePath": "api/CartItem/{id}",
    "HttpMethod": "DELETE",
    "IsController": true,
    "Order": 0,
    "Parameters": [
      {
        "Name": "id",
        "Type": "System.Int32",
        "IsRequired": true
      }
    ],
    "ReturnTypes": []
  },
  {
    "ContainingType": "BookStore.Controllers.CartItemController",
    "Method": "GetCartItemsByCartId",
    "RelativePath": "api/CartItem/cart/{cartId}",
    "HttpMethod": "GET",
    "IsController": true,
    "Order": 0,
    "Parameters": [
      {
        "Name": "cartId",
        "Type": "System.Int32",
        "IsRequired": true
      }
    ],
    "ReturnTypes": []
  },
  {
    "ContainingType": "BookStore.Controllers.CategoryController",
    "Method": "GetAllCategorys",
    "RelativePath": "api/Category",
    "HttpMethod": "GET",
    "IsController": true,
    "Order": 0,
    "Parameters": [],
    "ReturnTypes": []
  },
  {
    "ContainingType": "BookStore.Controllers.CategoryController",
    "Method": "CreateCategory",
    "RelativePath": "api/Category",
    "HttpMethod": "POST",
    "IsController": true,
    "Order": 0,
    "Parameters": [
      {
        "Name": "categoryDto",
        "Type": "BookStore.Dtos.CategoryDto",
        "IsRequired": true
      }
    ],
    "ReturnTypes": []
  },
  {
    "ContainingType": "BookStore.Controllers.CategoryController",
    "Method": "GetCategoryById",
    "RelativePath": "api/Category/{id}",
    "HttpMethod": "GET",
    "IsController": true,
    "Order": 0,
    "Parameters": [
      {
        "Name": "id",
        "Type": "System.Int32",
        "IsRequired": true
      }
    ],
    "ReturnTypes": []
  },
  {
    "ContainingType": "BookStore.Controllers.CategoryController",
    "Method": "UpdateCategory",
    "RelativePath": "api/Category/{id}",
    "HttpMethod": "PUT",
    "IsController": true,
    "Order": 0,
    "Parameters": [
      {
        "Name": "id",
        "Type": "System.Int32",
        "IsRequired": true
      },
      {
        "Name": "categoryDto",
        "Type": "BookStore.Dtos.CategoryDto",
        "IsRequired": true
      }
    ],
    "ReturnTypes": []
  },
  {
    "ContainingType": "BookStore.Controllers.CategoryController",
    "Method": "DeleteCategory",
    "RelativePath": "api/Category/{id}",
    "HttpMethod": "DELETE",
    "IsController": true,
    "Order": 0,
    "Parameters": [
      {
        "Name": "id",
        "Type": "System.Int32",
        "IsRequired": true
      }
    ],
    "ReturnTypes": []
  },
  {
    "ContainingType": "BookStore.Controllers.CategoryController",
    "Method": "CheckCategoryExists",
    "RelativePath": "api/Category/check",
    "HttpMethod": "GET",
    "IsController": true,
    "Order": 0,
    "Parameters": [
      {
        "Name": "name",
        "Type": "System.String",
        "IsRequired": false
      }
    ],
    "ReturnTypes": [
      {
        "Type": "System.Nullable\u00601[[System.Int32, System.Private.CoreLib, Version=8.0.0.0, Culture=neutral, PublicKeyToken=7cec85d7bea7798e]]",
        "MediaTypes": [
          "text/plain",
          "application/json",
          "text/json"
        ],
        "StatusCode": 200
      }
    ]
  },
  {
    "ContainingType": "BookStore.Controllers.ImageUploadController",
    "Method": "UploadImage",
    "RelativePath": "api/ImageUpload/upload",
    "HttpMethod": "POST",
    "IsController": true,
    "Order": 0,
    "Parameters": [
      {
        "Name": "file",
        "Type": "Microsoft.AspNetCore.Http.IFormFile",
        "IsRequired": false
      }
    ],
    "ReturnTypes": []
  },
  {
    "ContainingType": "BookStore.Controllers.OrderController",
    "Method": "GetAllOrders",
    "RelativePath": "api/Order",
    "HttpMethod": "GET",
    "IsController": true,
    "Order": 0,
    "Parameters": [
      {
        "Name": "page",
        "Type": "System.Int32",
        "IsRequired": false
      },
      {
        "Name": "pageSize",
        "Type": "System.Int32",
        "IsRequired": false
      },
      {
        "Name": "searchTerm",
        "Type": "System.String",
        "IsRequired": false
      },
      {
        "Name": "sortBy",
        "Type": "System.String",
        "IsRequired": false
      },
      {
        "Name": "sortDirection",
        "Type": "System.Boolean",
        "IsRequired": false
      }
    ],
    "ReturnTypes": []
  },
  {
    "ContainingType": "BookStore.Controllers.OrderController",
    "Method": "CreateOrder",
    "RelativePath": "api/Order",
    "HttpMethod": "POST",
    "IsController": true,
    "Order": 0,
    "Parameters": [
      {
        "Name": "createdOrderDto",
        "Type": "BookStore.Dtos.CreateOrderDto",
        "IsRequired": true
      }
    ],
    "ReturnTypes": []
  },
  {
    "ContainingType": "BookStore.Controllers.OrderController",
    "Method": "GetOrderById",
    "RelativePath": "api/Order/{id}",
    "HttpMethod": "GET",
    "IsController": true,
    "Order": 0,
    "Parameters": [
      {
        "Name": "id",
        "Type": "System.Int32",
        "IsRequired": true
      }
    ],
    "ReturnTypes": []
  },
  {
    "ContainingType": "BookStore.Controllers.OrderController",
    "Method": "UpdateOrderStatus",
    "RelativePath": "api/Order/{id}",
    "HttpMethod": "PUT",
    "IsController": true,
    "Order": 0,
    "Parameters": [
      {
        "Name": "id",
        "Type": "System.Int32",
        "IsRequired": true
      },
      {
        "Name": "status",
        "Type": "System.Int32",
        "IsRequired": false
      }
    ],
    "ReturnTypes": []
  },
  {
    "ContainingType": "BookStore.Controllers.OrderController",
    "Method": "DeleteOrder",
    "RelativePath": "api/Order/{id}",
    "HttpMethod": "DELETE",
    "IsController": true,
    "Order": 0,
    "Parameters": [
      {
        "Name": "id",
        "Type": "System.Int32",
        "IsRequired": true
      }
    ],
    "ReturnTypes": []
  },
  {
    "ContainingType": "BookStore.Controllers.OrderController",
    "Method": "GetOrdersByUserId",
    "RelativePath": "api/Order/user/{userId}",
    "HttpMethod": "GET",
    "IsController": true,
    "Order": 0,
    "Parameters": [
      {
        "Name": "userId",
        "Type": "System.Int32",
        "IsRequired": true
      },
      {
        "Name": "status",
        "Type": "System.Int32",
        "IsRequired": false
      }
    ],
    "ReturnTypes": []
  },
  {
    "ContainingType": "BookStore.Controllers.PaymentController",
    "Method": "GetAllPayments",
    "RelativePath": "api/Payment",
    "HttpMethod": "GET",
    "IsController": true,
    "Order": 0,
    "Parameters": [],
    "ReturnTypes": []
  },
  {
    "ContainingType": "BookStore.Controllers.PaymentController",
    "Method": "CreatePayment",
    "RelativePath": "api/Payment",
    "HttpMethod": "POST",
    "IsController": true,
    "Order": 0,
    "Parameters": [
      {
        "Name": "paymentDto",
        "Type": "BookStore.Dtos.PaymentDto",
        "IsRequired": true
      }
    ],
    "ReturnTypes": []
  },
  {
    "ContainingType": "BookStore.Controllers.PaymentController",
    "Method": "GetPaymentById",
    "RelativePath": "api/Payment/{id}",
    "HttpMethod": "GET",
    "IsController": true,
    "Order": 0,
    "Parameters": [
      {
        "Name": "id",
        "Type": "System.Int32",
        "IsRequired": true
      }
    ],
    "ReturnTypes": []
  },
  {
    "ContainingType": "BookStore.Controllers.PaymentController",
    "Method": "UpdatePayment",
    "RelativePath": "api/Payment/{id}",
    "HttpMethod": "PUT",
    "IsController": true,
    "Order": 0,
    "Parameters": [
      {
        "Name": "id",
        "Type": "System.Int32",
        "IsRequired": true
      },
      {
        "Name": "paymentDto",
        "Type": "BookStore.Dtos.PaymentDto",
        "IsRequired": true
      }
    ],
    "ReturnTypes": []
  },
  {
    "ContainingType": "BookStore.Controllers.PaymentController",
    "Method": "DeletePayment",
    "RelativePath": "api/Payment/{id}",
    "HttpMethod": "DELETE",
    "IsController": true,
    "Order": 0,
    "Parameters": [
      {
        "Name": "id",
        "Type": "System.Int32",
        "IsRequired": true
      }
    ],
    "ReturnTypes": []
  },
  {
    "ContainingType": "BookStore.Controllers.PublisherController",
    "Method": "GetAllPublishers",
    "RelativePath": "api/Publisher",
    "HttpMethod": "GET",
    "IsController": true,
    "Order": 0,
    "Parameters": [],
    "ReturnTypes": []
  },
  {
    "ContainingType": "BookStore.Controllers.PublisherController",
    "Method": "CreatePublisher",
    "RelativePath": "api/Publisher",
    "HttpMethod": "POST",
    "IsController": true,
    "Order": 0,
    "Parameters": [
      {
        "Name": "publisherDto",
        "Type": "BookStore.Dtos.PublisherDto",
        "IsRequired": true
      }
    ],
    "ReturnTypes": []
  },
  {
    "ContainingType": "BookStore.Controllers.PublisherController",
    "Method": "GetPublisherById",
    "RelativePath": "api/Publisher/{id}",
    "HttpMethod": "GET",
    "IsController": true,
    "Order": 0,
    "Parameters": [
      {
        "Name": "id",
        "Type": "System.Int32",
        "IsRequired": true
      }
    ],
    "ReturnTypes": []
  },
  {
    "ContainingType": "BookStore.Controllers.PublisherController",
    "Method": "UpdatePublisher",
    "RelativePath": "api/Publisher/{id}",
    "HttpMethod": "PUT",
    "IsController": true,
    "Order": 0,
    "Parameters": [
      {
        "Name": "id",
        "Type": "System.Int32",
        "IsRequired": true
      },
      {
        "Name": "publisherDto",
        "Type": "BookStore.Dtos.PublisherDto",
        "IsRequired": true
      }
    ],
    "ReturnTypes": []
  },
  {
    "ContainingType": "BookStore.Controllers.PublisherController",
    "Method": "DeletePublisher",
    "RelativePath": "api/Publisher/{id}",
    "HttpMethod": "DELETE",
    "IsController": true,
    "Order": 0,
    "Parameters": [
      {
        "Name": "id",
        "Type": "System.Int32",
        "IsRequired": true
      }
    ],
    "ReturnTypes": []
  },
  {
    "ContainingType": "BookStore.Controllers.PublisherController",
    "Method": "CheckCategoryExists",
    "RelativePath": "api/Publisher/check",
    "HttpMethod": "GET",
    "IsController": true,
    "Order": 0,
    "Parameters": [
      {
        "Name": "name",
        "Type": "System.String",
        "IsRequired": false
      }
    ],
    "ReturnTypes": [
      {
        "Type": "System.Nullable\u00601[[System.Int32, System.Private.CoreLib, Version=8.0.0.0, Culture=neutral, PublicKeyToken=7cec85d7bea7798e]]",
        "MediaTypes": [
          "text/plain",
          "application/json",
          "text/json"
        ],
        "StatusCode": 200
      }
    ]
  },
  {
    "ContainingType": "BookStore.Controllers.RatingController",
    "Method": "GetAllRatings",
    "RelativePath": "api/Rating",
    "HttpMethod": "GET",
    "IsController": true,
    "Order": 0,
    "Parameters": [],
    "ReturnTypes": []
  },
  {
    "ContainingType": "BookStore.Controllers.RatingController",
    "Method": "CreateRating",
    "RelativePath": "api/Rating",
    "HttpMethod": "POST",
    "IsController": true,
    "Order": 0,
    "Parameters": [
      {
        "Name": "ratingDto",
        "Type": "BookStore.Dtos.RatingDto",
        "IsRequired": true
      }
    ],
    "ReturnTypes": []
  },
  {
    "ContainingType": "BookStore.Controllers.RatingController",
    "Method": "GetRatingById",
    "RelativePath": "api/Rating/{id}",
    "HttpMethod": "GET",
    "IsController": true,
    "Order": 0,
    "Parameters": [
      {
        "Name": "id",
        "Type": "System.Int32",
        "IsRequired": true
      }
    ],
    "ReturnTypes": []
  },
  {
    "ContainingType": "BookStore.Controllers.RatingController",
    "Method": "UpdateRating",
    "RelativePath": "api/Rating/{id}",
    "HttpMethod": "PUT",
    "IsController": true,
    "Order": 0,
    "Parameters": [
      {
        "Name": "id",
        "Type": "System.Int32",
        "IsRequired": true
      },
      {
        "Name": "ratingDto",
        "Type": "BookStore.Dtos.RatingDto",
        "IsRequired": true
      }
    ],
    "ReturnTypes": []
  },
  {
    "ContainingType": "BookStore.Controllers.RatingController",
    "Method": "DeleteRating",
    "RelativePath": "api/Rating/{id}",
    "HttpMethod": "DELETE",
    "IsController": true,
    "Order": 0,
    "Parameters": [
      {
        "Name": "id",
        "Type": "System.Int32",
        "IsRequired": true
      }
    ],
    "ReturnTypes": []
  },
  {
    "ContainingType": "BookStore.Controllers.RatingController",
    "Method": "GetRatingsByBookId",
    "RelativePath": "api/Rating/book/{bookId}",
    "HttpMethod": "GET",
    "IsController": true,
    "Order": 0,
    "Parameters": [
      {
        "Name": "bookId",
        "Type": "System.Int32",
        "IsRequired": true
      },
      {
        "Name": "page",
        "Type": "System.Int32",
        "IsRequired": false
      },
      {
        "Name": "pageSize",
        "Type": "System.Int32",
        "IsRequired": false
      },
      {
        "Name": "ratingValue",
        "Type": "System.Nullable\u00601[[System.Int32, System.Private.CoreLib, Version=8.0.0.0, Culture=neutral, PublicKeyToken=7cec85d7bea7798e]]",
        "IsRequired": false
      },
      {
        "Name": "sortByDescending",
        "Type": "System.Boolean",
        "IsRequired": false
      }
    ],
    "ReturnTypes": []
  },
  {
    "ContainingType": "BookStore.Controllers.RatingController",
    "Method": "GetRatingCountByBookId",
    "RelativePath": "api/Rating/ratings/{bookId}",
    "HttpMethod": "GET",
    "IsController": true,
    "Order": 0,
    "Parameters": [
      {
        "Name": "bookId",
        "Type": "System.Int32",
        "IsRequired": true
      }
    ],
    "ReturnTypes": []
  },
  {
    "ContainingType": "BookStore.Controllers.ShipmentController",
    "Method": "GetAllShipments",
    "RelativePath": "api/Shipment",
    "HttpMethod": "GET",
    "IsController": true,
    "Order": 0,
    "Parameters": [],
    "ReturnTypes": []
  },
  {
    "ContainingType": "BookStore.Controllers.ShipmentController",
    "Method": "CreateShipment",
    "RelativePath": "api/Shipment",
    "HttpMethod": "POST",
    "IsController": true,
    "Order": 0,
    "Parameters": [
      {
        "Name": "shipmentDto",
        "Type": "BookStore.Dtos.ShipmentDto",
        "IsRequired": true
      }
    ],
    "ReturnTypes": []
  },
  {
    "ContainingType": "BookStore.Controllers.ShipmentController",
    "Method": "GetShipmentById",
    "RelativePath": "api/Shipment/{id}",
    "HttpMethod": "GET",
    "IsController": true,
    "Order": 0,
    "Parameters": [
      {
        "Name": "id",
        "Type": "System.Int32",
        "IsRequired": true
      }
    ],
    "ReturnTypes": []
  },
  {
    "ContainingType": "BookStore.Controllers.ShipmentController",
    "Method": "UpdateShipment",
    "RelativePath": "api/Shipment/{id}",
    "HttpMethod": "PUT",
    "IsController": true,
    "Order": 0,
    "Parameters": [
      {
        "Name": "id",
        "Type": "System.Int32",
        "IsRequired": true
      },
      {
        "Name": "shipmentDto",
        "Type": "BookStore.Dtos.ShipmentDto",
        "IsRequired": true
      }
    ],
    "ReturnTypes": []
  },
  {
    "ContainingType": "BookStore.Controllers.ShipmentController",
    "Method": "DeleteShipment",
    "RelativePath": "api/Shipment/{id}",
    "HttpMethod": "DELETE",
    "IsController": true,
    "Order": 0,
    "Parameters": [
      {
        "Name": "id",
        "Type": "System.Int32",
        "IsRequired": true
      }
    ],
    "ReturnTypes": []
  },
  {
    "ContainingType": "BookStore.Controllers.ShippingAddressController",
    "Method": "CreateShippingAddress",
    "RelativePath": "api/ShippingAddress",
    "HttpMethod": "POST",
    "IsController": true,
    "Order": 0,
    "Parameters": [
      {
        "Name": "shippingAddressDto",
        "Type": "BookStore.Dtos.ShippingAddressDto",
        "IsRequired": true
      }
    ],
    "ReturnTypes": []
  },
  {
    "ContainingType": "BookStore.Controllers.ShippingAddressController",
    "Method": "UpdateShippingAddress",
    "RelativePath": "api/ShippingAddress/{id}",
    "HttpMethod": "PUT",
    "IsController": true,
    "Order": 0,
    "Parameters": [
      {
        "Name": "id",
        "Type": "System.Int32",
        "IsRequired": true
      },
      {
        "Name": "shippingAddressDto",
        "Type": "BookStore.Dtos.ShippingAddressDto",
        "IsRequired": true
      }
    ],
    "ReturnTypes": []
  },
  {
    "ContainingType": "BookStore.Controllers.ShippingAddressController",
    "Method": "DeleteShippingAddress",
    "RelativePath": "api/ShippingAddress/{id}",
    "HttpMethod": "DELETE",
    "IsController": true,
    "Order": 0,
    "Parameters": [
      {
        "Name": "id",
        "Type": "System.Int32",
        "IsRequired": true
      }
    ],
    "ReturnTypes": []
  },
  {
    "ContainingType": "BookStore.Controllers.ShippingAddressController",
    "Method": "GetShippingAddressById",
    "RelativePath": "api/ShippingAddress/{id}",
    "HttpMethod": "GET",
    "IsController": true,
    "Order": 0,
    "Parameters": [
      {
        "Name": "id",
        "Type": "System.Int32",
        "IsRequired": true
      }
    ],
    "ReturnTypes": []
  },
  {
    "ContainingType": "BookStore.Controllers.ShippingAddressController",
    "Method": "GetShippingAddressesByUserId",
    "RelativePath": "api/ShippingAddress/user/{userId}",
    "HttpMethod": "GET",
    "IsController": true,
    "Order": 0,
    "Parameters": [
      {
        "Name": "userId",
        "Type": "System.Int32",
        "IsRequired": true
      }
    ],
    "ReturnTypes": []
  },
  {
    "ContainingType": "BookStore.Controllers.StatisticsController",
    "Method": "GetBooksSoldByDay",
    "RelativePath": "api/Statistics/books-sold-by-day",
    "HttpMethod": "GET",
    "IsController": true,
    "Order": 0,
    "Parameters": [
      {
        "Name": "date",
        "Type": "System.DateTime",
        "IsRequired": false
      }
    ],
    "ReturnTypes": []
  },
  {
    "ContainingType": "BookStore.Controllers.StatisticsController",
    "Method": "GetBooksSoldByQuarters",
    "RelativePath": "api/Statistics/books-sold-by-quarters",
    "HttpMethod": "GET",
    "IsController": true,
    "Order": 0,
    "Parameters": [
      {
        "Name": "year",
        "Type": "System.Int32",
        "IsRequired": false
      }
    ],
    "ReturnTypes": []
  },
  {
    "ContainingType": "BookStore.Controllers.StatisticsController",
    "Method": "GetBooksSoldByYear",
    "RelativePath": "api/Statistics/books-sold-by-year",
    "HttpMethod": "GET",
    "IsController": true,
    "Order": 0,
    "Parameters": [
      {
        "Name": "year",
        "Type": "System.Int32",
        "IsRequired": false
      }
    ],
    "ReturnTypes": []
  },
  {
    "ContainingType": "BookStore.Controllers.StatisticsController",
    "Method": "GetRatingsByQuarters",
    "RelativePath": "api/Statistics/ratings-by-quarters",
    "HttpMethod": "GET",
    "IsController": true,
    "Order": 0,
    "Parameters": [
      {
        "Name": "year",
        "Type": "System.Int32",
        "IsRequired": false
      }
    ],
    "ReturnTypes": []
  },
  {
    "ContainingType": "BookStore.Controllers.StatisticsController",
    "Method": "GetRatingsByYear",
    "RelativePath": "api/Statistics/ratings-by-year",
    "HttpMethod": "GET",
    "IsController": true,
    "Order": 0,
    "Parameters": [
      {
        "Name": "year",
        "Type": "System.Int32",
        "IsRequired": false
      }
    ],
    "ReturnTypes": []
  },
  {
    "ContainingType": "BookStore.Controllers.StatisticsController",
    "Method": "GetRatingsCountByDay",
    "RelativePath": "api/Statistics/ratings-count-by-day",
    "HttpMethod": "GET",
    "IsController": true,
    "Order": 0,
    "Parameters": [
      {
        "Name": "date",
        "Type": "System.DateTime",
        "IsRequired": false
      }
    ],
    "ReturnTypes": []
  },
  {
    "ContainingType": "BookStore.Controllers.StatisticsController",
    "Method": "GetRevenueByDay",
    "RelativePath": "api/Statistics/revenue-by-day",
    "HttpMethod": "GET",
    "IsController": true,
    "Order": 0,
    "Parameters": [
      {
        "Name": "date",
        "Type": "System.DateTime",
        "IsRequired": false
      }
    ],
    "ReturnTypes": []
  },
  {
    "ContainingType": "BookStore.Controllers.StatisticsController",
    "Method": "GetRevenueByQuarters",
    "RelativePath": "api/Statistics/revenue-by-quarters",
    "HttpMethod": "GET",
    "IsController": true,
    "Order": 0,
    "Parameters": [
      {
        "Name": "year",
        "Type": "System.Int32",
        "IsRequired": false
      }
    ],
    "ReturnTypes": []
  },
  {
    "ContainingType": "BookStore.Controllers.StatisticsController",
    "Method": "GetRevenueByYear",
    "RelativePath": "api/Statistics/revenue-by-year",
    "HttpMethod": "GET",
    "IsController": true,
    "Order": 0,
    "Parameters": [
      {
        "Name": "year",
        "Type": "System.Int32",
        "IsRequired": false
      }
    ],
    "ReturnTypes": []
  },
  {
    "ContainingType": "BookStore.Controllers.UserController",
    "Method": "GetAllUsers",
    "RelativePath": "api/User",
    "HttpMethod": "GET",
    "IsController": true,
    "Order": 0,
    "Parameters": [],
    "ReturnTypes": []
  },
  {
    "ContainingType": "BookStore.Controllers.UserController",
    "Method": "CreateUser",
    "RelativePath": "api/User",
    "HttpMethod": "POST",
    "IsController": true,
    "Order": 0,
    "Parameters": [
      {
        "Name": "userDto",
        "Type": "BookStore.Dtos.UserDto",
        "IsRequired": true
      }
    ],
    "ReturnTypes": []
  },
  {
    "ContainingType": "BookStore.Controllers.UserController",
    "Method": "GetUserById",
    "RelativePath": "api/User/{id}",
    "HttpMethod": "GET",
    "IsController": true,
    "Order": 0,
    "Parameters": [
      {
        "Name": "id",
        "Type": "System.Int32",
        "IsRequired": true
      }
    ],
    "ReturnTypes": []
  },
  {
    "ContainingType": "BookStore.Controllers.UserController",
    "Method": "UpdateUser",
    "RelativePath": "api/User/{id}",
    "HttpMethod": "PUT",
    "IsController": true,
    "Order": 0,
    "Parameters": [
      {
        "Name": "id",
        "Type": "System.Int32",
        "IsRequired": true
      },
      {
        "Name": "userDto",
        "Type": "BookStore.Dtos.UserDto",
        "IsRequired": true
      }
    ],
    "ReturnTypes": []
  },
  {
    "ContainingType": "BookStore.Controllers.UserController",
    "Method": "DeleteUser",
    "RelativePath": "api/User/{id}",
    "HttpMethod": "DELETE",
    "IsController": true,
    "Order": 0,
    "Parameters": [
      {
        "Name": "id",
        "Type": "System.Int32",
        "IsRequired": true
      }
    ],
    "ReturnTypes": []
  }
]